Metadata-Version: 2.2
Name: predpca-py
Version: 0.1.2
Summary: PredPCA: Predictive Principal Component Analysis
Author-email: Takuya Isomura <takuya.isomura@riken.jp>
Maintainer-email: Araya Research DX <araya-researchdx-service@araya.org>
License:                     GNU GENERAL PUBLIC LICENSE
Project-URL: Repository, https://github.com/takuyaisomura/predpca-py
Project-URL: Bug Tracker, https://github.com/takuyaisomura/predpca-py/issues
Classifier: Programming Language :: Python :: 3
Classifier: License :: OSI Approved :: GNU General Public License v3 or later (GPLv3+)
Classifier: Operating System :: OS Independent
Classifier: Topic :: Scientific/Engineering
Requires-Python: >=3.9
License-File: LICENSE
Requires-Dist: numpy
Requires-Dist: scipy
Requires-Dist: pandas
Requires-Dist: matplotlib
Requires-Dist: seaborn
Requires-Dist: scikit-learn
Requires-Dist: ffmpeg-python
Requires-Dist: moviepy
Requires-Dist: scikit-image
Requires-Dist: tqdm
